{"type": "Request",
    "id": "123", 
    "method": "SEND", 
    "params": {
        "measures": [ 
            ["Commodity_VegaSens", "sum"],
["Commodity_VegaSens_Weighted", "sum"],
["Commodity_VegaSb", "first"],
["Commodity_VegaKb_Low", "first"],
["Commodity_VegaKb_Medium", "first"],
["Commodity_VegaKb_High", "first"],
["Commodity_VegaCharge_Low", "first"],
["Commodity_VegaCharge_Medium", "first"],
["Commodity_VegaCharge_High", "first"]
                ],
        "groupby": ["Desk"],
        "filters": [],
        "optional_params": {
                    "hide_zeros": true,
                    "calc_params": {"jurisdiction": "BCBS"}
                }
    }
}